<mediawiki xmlns="http://www.mediawiki.org/xml/export-0.10/" xmlns:xsi="http://www.w3.org/2001/XMLSchema-instance" xsi:schemaLocation="http://www.mediawiki.org/xml/export-0.10/ http://www.mediawiki.org/xml/export-0.10.xsd" version="0.10" xml:lang="en">
  <siteinfo>
    <sitename>Wikidata</sitename>
    <dbname>wikidatawiki</dbname>
    <base>https://www.wikidata.org/wiki/Wikidata:Main_Page</base>
    <generator>MediaWiki 1.38.0-wmf.25</generator>
    <case>first-letter</case>
    <namespaces>
      <namespace key="-2" case="first-letter">Media</namespace>
      <namespace key="-1" case="first-letter">Special</namespace>
      <namespace key="0" case="first-letter" />
      <namespace key="1" case="first-letter">Talk</namespace>
      <namespace key="2" case="first-letter">User</namespace>
      <namespace key="3" case="first-letter">User talk</namespace>
      <namespace key="4" case="first-letter">Wikidata</namespace>
      <namespace key="5" case="first-letter">Wikidata talk</namespace>
      <namespace key="6" case="first-letter">File</namespace>
      <namespace key="7" case="first-letter">File talk</namespace>
      <namespace key="8" case="first-letter">MediaWiki</namespace>
      <namespace key="9" case="first-letter">MediaWiki talk</namespace>
      <namespace key="10" case="first-letter">Template</namespace>
      <namespace key="11" case="first-letter">Template talk</namespace>
      <namespace key="12" case="first-letter">Help</namespace>
      <namespace key="13" case="first-letter">Help talk</namespace>
      <namespace key="14" case="first-letter">Category</namespace>
      <namespace key="15" case="first-letter">Category talk</namespace>
      <namespace key="120" case="first-letter">Property</namespace>
      <namespace key="121" case="first-letter">Property talk</namespace>
      <namespace key="122" case="first-letter">Query</namespace>
      <namespace key="123" case="first-letter">Query talk</namespace>
      <namespace key="146" case="first-letter">Lexeme</namespace>
      <namespace key="147" case="first-letter">Lexeme talk</namespace>
      <namespace key="640" case="first-letter">EntitySchema</namespace>
      <namespace key="641" case="first-letter">EntitySchema talk</namespace>
      <namespace key="828" case="first-letter">Module</namespace>
      <namespace key="829" case="first-letter">Module talk</namespace>
      <namespace key="1198" case="first-letter">Translations</namespace>
      <namespace key="1199" case="first-letter">Translations talk</namespace>
      <namespace key="2300" case="first-letter">Gadget</namespace>
      <namespace key="2301" case="first-letter">Gadget talk</namespace>
      <namespace key="2302" case="case-sensitive">Gadget definition</namespace>
      <namespace key="2303" case="case-sensitive">Gadget definition talk</namespace>
      <namespace key="2600" case="first-letter">Topic</namespace>
    </namespaces>
  </siteinfo>
  <page>
    <title>Q105743918</title>
    <ns>0</ns>
    <id>101105299</id>
    <revision>
      <id>1374421734</id>
      <timestamp>2021-03-03T10:39:26Z</timestamp>
      <contributor>
        <username>Rdmpage</username>
        <id>109040</id>
      </contributor>
      <comment>/* wbeditentity-create-item:0| */ #quickstatements; #temporary_batch_1614767776083</comment>
      <model>wikibase-item</model>
      <format>application/json</format>
      <text bytes="9580" xml:space="preserve">{"type":"item","id":"Q105743918","labels":{"en":{"language":"en","value":"Allium lopadusanum (Liliaceae), a New Species from Lampedusa (Sicily)"}},"descriptions":[],"aliases":[],"claims":{"P407":[{"mainsnak":{"snaktype":"value","property":"P407","hash":"daf1c4fcb58181b02dff9cc89deb084004ddae4b","datavalue":{"value":{"entity-type":"item","numeric-id":1860,"id":"Q1860"},"type":"wikibase-entityid"}},"type":"statement","id":"Q105743918$A04688AE-2938-4646-A31E-198C6678038B","rank":"normal"}],"P1476":[{"mainsnak":{"snaktype":"value","property":"P1476","hash":"1163ea7e6cce74f0eefc7a29c8487d839abfc367","datavalue":{"value":{"text":"Allium lopadusanum (Liliaceae), a New Species from Lampedusa (Sicily)","language":"en"},"type":"monolingualtext"}},"type":"statement","id":"Q105743918$F718B3B0-3DCA-46CA-86CF-A63750767A10","rank":"normal","references":[{"hash":"8408ce78a981253dfb4653c56fef4ce7302d3150","snaks":{"P248":[{"snaktype":"value","property":"P248","hash":"71000ade3e2d3e332c52d5e596bcb34c3efeef6f","datavalue":{"value":{"entity-type":"item","numeric-id":1420342,"id":"Q1420342"},"type":"wikibase-entityid"}}],"P854":[{"snaktype":"value","property":"P854","hash":"94bdf5a2a925ff5aa8918ee4c2fda9dc8062c34e","datavalue":{"value":"https:\/\/www.jstor.org\/stable\/3996306","type":"string"}}]},"snaks-order":["P248","P854"]}]}],"P31":[{"mainsnak":{"snaktype":"value","property":"P31","hash":"29465f78f13add11b617f0de4ade56cd1122c19c","datavalue":{"value":{"entity-type":"item","numeric-id":13442814,"id":"Q13442814"},"type":"wikibase-entityid"}},"type":"statement","id":"Q105743918$97926E20-FAED-4CA4-8D9E-2E2843ACD21E","rank":"normal","references":[{"hash":"8408ce78a981253dfb4653c56fef4ce7302d3150","snaks":{"P248":[{"snaktype":"value","property":"P248","hash":"71000ade3e2d3e332c52d5e596bcb34c3efeef6f","datavalue":{"value":{"entity-type":"item","numeric-id":1420342,"id":"Q1420342"},"type":"wikibase-entityid"}}],"P854":[{"snaktype":"value","property":"P854","hash":"94bdf5a2a925ff5aa8918ee4c2fda9dc8062c34e","datavalue":{"value":"https:\/\/www.jstor.org\/stable\/3996306","type":"string"}}]},"snaks-order":["P248","P854"]}]}],"P577":[{"mainsnak":{"snaktype":"value","property":"P577","hash":"9a17e46d4a2f0a91dbc56bf472d514cba2368eaf","datavalue":{"value":{"time":"+1986-00-00T00:00:00Z","timezone":0,"before":0,"after":0,"precision":9,"calendarmodel":"http:\/\/www.wikidata.org\/entity\/Q1985727"},"type":"time"}},"type":"statement","id":"Q105743918$641C4895-A058-480A-A278-4E34A0D2479C","rank":"normal","references":[{"hash":"8408ce78a981253dfb4653c56fef4ce7302d3150","snaks":{"P248":[{"snaktype":"value","property":"P248","hash":"71000ade3e2d3e332c52d5e596bcb34c3efeef6f","datavalue":{"value":{"entity-type":"item","numeric-id":1420342,"id":"Q1420342"},"type":"wikibase-entityid"}}],"P854":[{"snaktype":"value","property":"P854","hash":"94bdf5a2a925ff5aa8918ee4c2fda9dc8062c34e","datavalue":{"value":"https:\/\/www.jstor.org\/stable\/3996306","type":"string"}}]},"snaks-order":["P248","P854"]}]}],"P2093":[{"mainsnak":{"snaktype":"value","property":"P2093","hash":"1fe694103159413d47d092e517346eb37b1058dd","datavalue":{"value":"Giuseppina Bartolo","type":"string"}},"type":"statement","qualifiers":{"P1545":[{"snaktype":"value","property":"P1545","hash":"2a1ced1dca90648ea7e306acbadd74fc81a10722","datavalue":{"value":"1","type":"string"}}]},"qualifiers-order":["P1545"],"id":"Q105743918$4B2B796C-5AF8-4933-B4D1-CCEEF7A132CA","rank":"normal","references":[{"hash":"8408ce78a981253dfb4653c56fef4ce7302d3150","snaks":{"P248":[{"snaktype":"value","property":"P248","hash":"71000ade3e2d3e332c52d5e596bcb34c3efeef6f","datavalue":{"value":{"entity-type":"item","numeric-id":1420342,"id":"Q1420342"},"type":"wikibase-entityid"}}],"P854":[{"snaktype":"value","property":"P854","hash":"94bdf5a2a925ff5aa8918ee4c2fda9dc8062c34e","datavalue":{"value":"https:\/\/www.jstor.org\/stable\/3996306","type":"string"}}]},"snaks-order":["P248","P854"]}]},{"mainsnak":{"snaktype":"value","property":"P2093","hash":"161499798147731ba31661e941d312bc53906041","datavalue":{"value":"Salvatore Brullo","type":"string"}},"type":"statement","qualifiers":{"P1545":[{"snaktype":"value","property":"P1545","hash":"7241753c62a310cf84895620ea82250dcea65835","datavalue":{"value":"2","type":"string"}}]},"qualifiers-order":["P1545"],"id":"Q105743918$5172C6C5-73A2-4AEB-9229-BB6DDAD1C6A0","rank":"normal","references":[{"hash":"8408ce78a981253dfb4653c56fef4ce7302d3150","snaks":{"P248":[{"snaktype":"value","property":"P248","hash":"71000ade3e2d3e332c52d5e596bcb34c3efeef6f","datavalue":{"value":{"entity-type":"item","numeric-id":1420342,"id":"Q1420342"},"type":"wikibase-entityid"}}],"P854":[{"snaktype":"value","property":"P854","hash":"94bdf5a2a925ff5aa8918ee4c2fda9dc8062c34e","datavalue":{"value":"https:\/\/www.jstor.org\/stable\/3996306","type":"string"}}]},"snaks-order":["P248","P854"]}]},{"mainsnak":{"snaktype":"value","property":"P2093","hash":"e149c359421c20951780e93765aa4f85af2ad52e","datavalue":{"value":"Pietro Pavone","type":"string"}},"type":"statement","qualifiers":{"P1545":[{"snaktype":"value","property":"P1545","hash":"0e979f28bf306fefdcd352b4eb8dee5da2153a6d","datavalue":{"value":"3","type":"string"}}]},"qualifiers-order":["P1545"],"id":"Q105743918$1B245665-65D9-48A5-8C59-A7FB35E37679","rank":"normal","references":[{"hash":"8408ce78a981253dfb4653c56fef4ce7302d3150","snaks":{"P248":[{"snaktype":"value","property":"P248","hash":"71000ade3e2d3e332c52d5e596bcb34c3efeef6f","datavalue":{"value":{"entity-type":"item","numeric-id":1420342,"id":"Q1420342"},"type":"wikibase-entityid"}}],"P854":[{"snaktype":"value","property":"P854","hash":"94bdf5a2a925ff5aa8918ee4c2fda9dc8062c34e","datavalue":{"value":"https:\/\/www.jstor.org\/stable\/3996306","type":"string"}}]},"snaks-order":["P248","P854"]}]}],"P1433":[{"mainsnak":{"snaktype":"value","property":"P1433","hash":"ad755d34ad4505b3a1dcd4a698a14bce870a0615","datavalue":{"value":{"entity-type":"item","numeric-id":2675951,"id":"Q2675951"},"type":"wikibase-entityid"}},"type":"statement","id":"Q105743918$030BDE6F-1629-47A7-9829-3DEE2182F150","rank":"normal","references":[{"hash":"8408ce78a981253dfb4653c56fef4ce7302d3150","snaks":{"P248":[{"snaktype":"value","property":"P248","hash":"71000ade3e2d3e332c52d5e596bcb34c3efeef6f","datavalue":{"value":{"entity-type":"item","numeric-id":1420342,"id":"Q1420342"},"type":"wikibase-entityid"}}],"P854":[{"snaktype":"value","property":"P854","hash":"94bdf5a2a925ff5aa8918ee4c2fda9dc8062c34e","datavalue":{"value":"https:\/\/www.jstor.org\/stable\/3996306","type":"string"}}]},"snaks-order":["P248","P854"]}]}],"P478":[{"mainsnak":{"snaktype":"value","property":"P478","hash":"c6d9ab79d7e0a7bda3a388ebe3dd94a2da80b455","datavalue":{"value":"16","type":"string"}},"type":"statement","id":"Q105743918$9F027078-3362-431A-BAE9-104DBAEAE511","rank":"normal","references":[{"hash":"8408ce78a981253dfb4653c56fef4ce7302d3150","snaks":{"P248":[{"snaktype":"value","property":"P248","hash":"71000ade3e2d3e332c52d5e596bcb34c3efeef6f","datavalue":{"value":{"entity-type":"item","numeric-id":1420342,"id":"Q1420342"},"type":"wikibase-entityid"}}],"P854":[{"snaktype":"value","property":"P854","hash":"94bdf5a2a925ff5aa8918ee4c2fda9dc8062c34e","datavalue":{"value":"https:\/\/www.jstor.org\/stable\/3996306","type":"string"}}]},"snaks-order":["P248","P854"]}]}],"P433":[{"mainsnak":{"snaktype":"value","property":"P433","hash":"962ed10012ef254020e2a8c8a6c8ba7647d35a12","datavalue":{"value":"1","type":"string"}},"type":"statement","id":"Q105743918$D4BA6074-FD53-4675-8D7C-8C214975BFC6","rank":"normal","references":[{"hash":"8408ce78a981253dfb4653c56fef4ce7302d3150","snaks":{"P248":[{"snaktype":"value","property":"P248","hash":"71000ade3e2d3e332c52d5e596bcb34c3efeef6f","datavalue":{"value":{"entity-type":"item","numeric-id":1420342,"id":"Q1420342"},"type":"wikibase-entityid"}}],"P854":[{"snaktype":"value","property":"P854","hash":"94bdf5a2a925ff5aa8918ee4c2fda9dc8062c34e","datavalue":{"value":"https:\/\/www.jstor.org\/stable\/3996306","type":"string"}}]},"snaks-order":["P248","P854"]}]}],"P304":[{"mainsnak":{"snaktype":"value","property":"P304","hash":"3b88738ced1cf84f9d4e94adc914d41034492775","datavalue":{"value":"89-93","type":"string"}},"type":"statement","id":"Q105743918$F199F168-C27A-4083-A523-A84748C0320E","rank":"normal","references":[{"hash":"8408ce78a981253dfb4653c56fef4ce7302d3150","snaks":{"P248":[{"snaktype":"value","property":"P248","hash":"71000ade3e2d3e332c52d5e596bcb34c3efeef6f","datavalue":{"value":{"entity-type":"item","numeric-id":1420342,"id":"Q1420342"},"type":"wikibase-entityid"}}],"P854":[{"snaktype":"value","property":"P854","hash":"94bdf5a2a925ff5aa8918ee4c2fda9dc8062c34e","datavalue":{"value":"https:\/\/www.jstor.org\/stable\/3996306","type":"string"}}]},"snaks-order":["P248","P854"]}]}],"P888":[{"mainsnak":{"snaktype":"value","property":"P888","hash":"c4a8b3b709e456cebfdfa9ee47fd860368de65f9","datavalue":{"value":"3996306","type":"string"}},"type":"statement","id":"Q105743918$0CBEED53-21A6-4537-B3CE-923D2DAF190C","rank":"normal","references":[{"hash":"8408ce78a981253dfb4653c56fef4ce7302d3150","snaks":{"P248":[{"snaktype":"value","property":"P248","hash":"71000ade3e2d3e332c52d5e596bcb34c3efeef6f","datavalue":{"value":{"entity-type":"item","numeric-id":1420342,"id":"Q1420342"},"type":"wikibase-entityid"}}],"P854":[{"snaktype":"value","property":"P854","hash":"94bdf5a2a925ff5aa8918ee4c2fda9dc8062c34e","datavalue":{"value":"https:\/\/www.jstor.org\/stable\/3996306","type":"string"}}]},"snaks-order":["P248","P854"]}]}]},"sitelinks":[]}</text>
      <sha1>d094z2bs106qvznr41flkkwllmjj19f</sha1>
    </revision>
    <revision>
      <id>1374433391</id>
      <parentid>1374421734</parentid>
      <timestamp>2021-03-03T11:10:28Z</timestamp>
      <contributor>
        <username>Edoderoobot</username>
        <id>1554155</id>
      </contributor>
      <comment>/* wbeditentity-update-languages-short:0||nl */ nl-description, [[User:Edoderoobot/Set-nl-description|python code]] - wetenschappelijk artikel</comment>
      <model>wikibase-item</model>
      <format>application/json</format>
      <text bytes="9740" xml:space="preserve">{"type":"item","id":"Q105743918","labels":{"en":{"language":"en","value":"Allium lopadusanum (Liliaceae), a New Species from Lampedusa (Sicily)"},"nl":{"language":"nl","value":"Allium lopadusanum (Liliaceae), a New Species from Lampedusa (Sicily)"}},"descriptions":{"nl":{"language":"nl","value":"wetenschappelijk artikel"}},"aliases":[],"claims":{"P407":[{"mainsnak":{"snaktype":"value","property":"P407","hash":"daf1c4fcb58181b02dff9cc89deb084004ddae4b","datavalue":{"value":{"entity-type":"item","numeric-id":1860,"id":"Q1860"},"type":"wikibase-entityid"}},"type":"statement","id":"Q105743918$A04688AE-2938-4646-A31E-198C6678038B","rank":"normal"}],"P1476":[{"mainsnak":{"snaktype":"value","property":"P1476","hash":"1163ea7e6cce74f0eefc7a29c8487d839abfc367","datavalue":{"value":{"text":"Allium lopadusanum (Liliaceae), a New Species from Lampedusa (Sicily)","language":"en"},"type":"monolingualtext"}},"type":"statement","id":"Q105743918$F718B3B0-3DCA-46CA-86CF-A63750767A10","rank":"normal","references":[{"hash":"8408ce78a981253dfb4653c56fef4ce7302d3150","snaks":{"P248":[{"snaktype":"value","property":"P248","hash":"71000ade3e2d3e332c52d5e596bcb34c3efeef6f","datavalue":{"value":{"entity-type":"item","numeric-id":1420342,"id":"Q1420342"},"type":"wikibase-entityid"}}],"P854":[{"snaktype":"value","property":"P854","hash":"94bdf5a2a925ff5aa8918ee4c2fda9dc8062c34e","datavalue":{"value":"https:\/\/www.jstor.org\/stable\/3996306","type":"string"}}]},"snaks-order":["P248","P854"]}]}],"P31":[{"mainsnak":{"snaktype":"value","property":"P31","hash":"29465f78f13add11b617f0de4ade56cd1122c19c","datavalue":{"value":{"entity-type":"item","numeric-id":13442814,"id":"Q13442814"},"type":"wikibase-entityid"}},"type":"statement","id":"Q105743918$97926E20-FAED-4CA4-8D9E-2E2843ACD21E","rank":"normal","references":[{"hash":"8408ce78a981253dfb4653c56fef4ce7302d3150","snaks":{"P248":[{"snaktype":"value","property":"P248","hash":"71000ade3e2d3e332c52d5e596bcb34c3efeef6f","datavalue":{"value":{"entity-type":"item","numeric-id":1420342,"id":"Q1420342"},"type":"wikibase-entityid"}}],"P854":[{"snaktype":"value","property":"P854","hash":"94bdf5a2a925ff5aa8918ee4c2fda9dc8062c34e","datavalue":{"value":"https:\/\/www.jstor.org\/stable\/3996306","type":"string"}}]},"snaks-order":["P248","P854"]}]}],"P577":[{"mainsnak":{"snaktype":"value","property":"P577","hash":"9a17e46d4a2f0a91dbc56bf472d514cba2368eaf","datavalue":{"value":{"time":"+1986-00-00T00:00:00Z","timezone":0,"before":0,"after":0,"precision":9,"calendarmodel":"http:\/\/www.wikidata.org\/entity\/Q1985727"},"type":"time"}},"type":"statement","id":"Q105743918$641C4895-A058-480A-A278-4E34A0D2479C","rank":"normal","references":[{"hash":"8408ce78a981253dfb4653c56fef4ce7302d3150","snaks":{"P248":[{"snaktype":"value","property":"P248","hash":"71000ade3e2d3e332c52d5e596bcb34c3efeef6f","datavalue":{"value":{"entity-type":"item","numeric-id":1420342,"id":"Q1420342"},"type":"wikibase-entityid"}}],"P854":[{"snaktype":"value","property":"P854","hash":"94bdf5a2a925ff5aa8918ee4c2fda9dc8062c34e","datavalue":{"value":"https:\/\/www.jstor.org\/stable\/3996306","type":"string"}}]},"snaks-order":["P248","P854"]}]}],"P2093":[{"mainsnak":{"snaktype":"value","property":"P2093","hash":"1fe694103159413d47d092e517346eb37b1058dd","datavalue":{"value":"Giuseppina Bartolo","type":"string"}},"type":"statement","qualifiers":{"P1545":[{"snaktype":"value","property":"P1545","hash":"2a1ced1dca90648ea7e306acbadd74fc81a10722","datavalue":{"value":"1","type":"string"}}]},"qualifiers-order":["P1545"],"id":"Q105743918$4B2B796C-5AF8-4933-B4D1-CCEEF7A132CA","rank":"normal","references":[{"hash":"8408ce78a981253dfb4653c56fef4ce7302d3150","snaks":{"P248":[{"snaktype":"value","property":"P248","hash":"71000ade3e2d3e332c52d5e596bcb34c3efeef6f","datavalue":{"value":{"entity-type":"item","numeric-id":1420342,"id":"Q1420342"},"type":"wikibase-entityid"}}],"P854":[{"snaktype":"value","property":"P854","hash":"94bdf5a2a925ff5aa8918ee4c2fda9dc8062c34e","datavalue":{"value":"https:\/\/www.jstor.org\/stable\/3996306","type":"string"}}]},"snaks-order":["P248","P854"]}]},{"mainsnak":{"snaktype":"value","property":"P2093","hash":"161499798147731ba31661e941d312bc53906041","datavalue":{"value":"Salvatore Brullo","type":"string"}},"type":"statement","qualifiers":{"P1545":[{"snaktype":"value","property":"P1545","hash":"7241753c62a310cf84895620ea82250dcea65835","datavalue":{"value":"2","type":"string"}}]},"qualifiers-order":["P1545"],"id":"Q105743918$5172C6C5-73A2-4AEB-9229-BB6DDAD1C6A0","rank":"normal","references":[{"hash":"8408ce78a981253dfb4653c56fef4ce7302d3150","snaks":{"P248":[{"snaktype":"value","property":"P248","hash":"71000ade3e2d3e332c52d5e596bcb34c3efeef6f","datavalue":{"value":{"entity-type":"item","numeric-id":1420342,"id":"Q1420342"},"type":"wikibase-entityid"}}],"P854":[{"snaktype":"value","property":"P854","hash":"94bdf5a2a925ff5aa8918ee4c2fda9dc8062c34e","datavalue":{"value":"https:\/\/www.jstor.org\/stable\/3996306","type":"string"}}]},"snaks-order":["P248","P854"]}]},{"mainsnak":{"snaktype":"value","property":"P2093","hash":"e149c359421c20951780e93765aa4f85af2ad52e","datavalue":{"value":"Pietro Pavone","type":"string"}},"type":"statement","qualifiers":{"P1545":[{"snaktype":"value","property":"P1545","hash":"0e979f28bf306fefdcd352b4eb8dee5da2153a6d","datavalue":{"value":"3","type":"string"}}]},"qualifiers-order":["P1545"],"id":"Q105743918$1B245665-65D9-48A5-8C59-A7FB35E37679","rank":"normal","references":[{"hash":"8408ce78a981253dfb4653c56fef4ce7302d3150","snaks":{"P248":[{"snaktype":"value","property":"P248","hash":"71000ade3e2d3e332c52d5e596bcb34c3efeef6f","datavalue":{"value":{"entity-type":"item","numeric-id":1420342,"id":"Q1420342"},"type":"wikibase-entityid"}}],"P854":[{"snaktype":"value","property":"P854","hash":"94bdf5a2a925ff5aa8918ee4c2fda9dc8062c34e","datavalue":{"value":"https:\/\/www.jstor.org\/stable\/3996306","type":"string"}}]},"snaks-order":["P248","P854"]}]}],"P1433":[{"mainsnak":{"snaktype":"value","property":"P1433","hash":"ad755d34ad4505b3a1dcd4a698a14bce870a0615","datavalue":{"value":{"entity-type":"item","numeric-id":2675951,"id":"Q2675951"},"type":"wikibase-entityid"}},"type":"statement","id":"Q105743918$030BDE6F-1629-47A7-9829-3DEE2182F150","rank":"normal","references":[{"hash":"8408ce78a981253dfb4653c56fef4ce7302d3150","snaks":{"P248":[{"snaktype":"value","property":"P248","hash":"71000ade3e2d3e332c52d5e596bcb34c3efeef6f","datavalue":{"value":{"entity-type":"item","numeric-id":1420342,"id":"Q1420342"},"type":"wikibase-entityid"}}],"P854":[{"snaktype":"value","property":"P854","hash":"94bdf5a2a925ff5aa8918ee4c2fda9dc8062c34e","datavalue":{"value":"https:\/\/www.jstor.org\/stable\/3996306","type":"string"}}]},"snaks-order":["P248","P854"]}]}],"P478":[{"mainsnak":{"snaktype":"value","property":"P478","hash":"c6d9ab79d7e0a7bda3a388ebe3dd94a2da80b455","datavalue":{"value":"16","type":"string"}},"type":"statement","id":"Q105743918$9F027078-3362-431A-BAE9-104DBAEAE511","rank":"normal","references":[{"hash":"8408ce78a981253dfb4653c56fef4ce7302d3150","snaks":{"P248":[{"snaktype":"value","property":"P248","hash":"71000ade3e2d3e332c52d5e596bcb34c3efeef6f","datavalue":{"value":{"entity-type":"item","numeric-id":1420342,"id":"Q1420342"},"type":"wikibase-entityid"}}],"P854":[{"snaktype":"value","property":"P854","hash":"94bdf5a2a925ff5aa8918ee4c2fda9dc8062c34e","datavalue":{"value":"https:\/\/www.jstor.org\/stable\/3996306","type":"string"}}]},"snaks-order":["P248","P854"]}]}],"P433":[{"mainsnak":{"snaktype":"value","property":"P433","hash":"962ed10012ef254020e2a8c8a6c8ba7647d35a12","datavalue":{"value":"1","type":"string"}},"type":"statement","id":"Q105743918$D4BA6074-FD53-4675-8D7C-8C214975BFC6","rank":"normal","references":[{"hash":"8408ce78a981253dfb4653c56fef4ce7302d3150","snaks":{"P248":[{"snaktype":"value","property":"P248","hash":"71000ade3e2d3e332c52d5e596bcb34c3efeef6f","datavalue":{"value":{"entity-type":"item","numeric-id":1420342,"id":"Q1420342"},"type":"wikibase-entityid"}}],"P854":[{"snaktype":"value","property":"P854","hash":"94bdf5a2a925ff5aa8918ee4c2fda9dc8062c34e","datavalue":{"value":"https:\/\/www.jstor.org\/stable\/3996306","type":"string"}}]},"snaks-order":["P248","P854"]}]}],"P304":[{"mainsnak":{"snaktype":"value","property":"P304","hash":"3b88738ced1cf84f9d4e94adc914d41034492775","datavalue":{"value":"89-93","type":"string"}},"type":"statement","id":"Q105743918$F199F168-C27A-4083-A523-A84748C0320E","rank":"normal","references":[{"hash":"8408ce78a981253dfb4653c56fef4ce7302d3150","snaks":{"P248":[{"snaktype":"value","property":"P248","hash":"71000ade3e2d3e332c52d5e596bcb34c3efeef6f","datavalue":{"value":{"entity-type":"item","numeric-id":1420342,"id":"Q1420342"},"type":"wikibase-entityid"}}],"P854":[{"snaktype":"value","property":"P854","hash":"94bdf5a2a925ff5aa8918ee4c2fda9dc8062c34e","datavalue":{"value":"https:\/\/www.jstor.org\/stable\/3996306","type":"string"}}]},"snaks-order":["P248","P854"]}]}],"P888":[{"mainsnak":{"snaktype":"value","property":"P888","hash":"c4a8b3b709e456cebfdfa9ee47fd860368de65f9","datavalue":{"value":"3996306","type":"string"}},"type":"statement","id":"Q105743918$0CBEED53-21A6-4537-B3CE-923D2DAF190C","rank":"normal","references":[{"hash":"8408ce78a981253dfb4653c56fef4ce7302d3150","snaks":{"P248":[{"snaktype":"value","property":"P248","hash":"71000ade3e2d3e332c52d5e596bcb34c3efeef6f","datavalue":{"value":{"entity-type":"item","numeric-id":1420342,"id":"Q1420342"},"type":"wikibase-entityid"}}],"P854":[{"snaktype":"value","property":"P854","hash":"94bdf5a2a925ff5aa8918ee4c2fda9dc8062c34e","datavalue":{"value":"https:\/\/www.jstor.org\/stable\/3996306","type":"string"}}]},"snaks-order":["P248","P854"]}]}]},"sitelinks":[]}</text>
      <sha1>mauxqtf5m5m0hzi3p0lma19oj008gm9</sha1>
    </revision>
    <revision>
      <id>1469315956</id>
      <parentid>1374433391</parentid>
      <timestamp>2021-07-29T23:18:16Z</timestamp>
      <contributor>
        <username>Hogü-456</username>
        <id>1790718</id>
      </contributor>
      <comment>/* wbsetdescription-add:1|de */ im Jahr 1986 veröffentlichter wissenschaftlicher Artikel, [[:toollabs:quickstatements/#/batch/60482|batch #60482]]</comment>
      <model>wikibase-item</model>
      <format>application/json</format>
      <text bytes="9835" xml:space="preserve">{"type":"item","id":"Q105743918","labels":{"en":{"language":"en","value":"Allium lopadusanum (Liliaceae), a New Species from Lampedusa (Sicily)"},"nl":{"language":"nl","value":"Allium lopadusanum (Liliaceae), a New Species from Lampedusa (Sicily)"}},"descriptions":{"nl":{"language":"nl","value":"wetenschappelijk artikel"},"de":{"language":"de","value":"im Jahr 1986 ver\u00f6ffentlichter wissenschaftlicher Artikel"}},"aliases":[],"claims":{"P407":[{"mainsnak":{"snaktype":"value","property":"P407","hash":"daf1c4fcb58181b02dff9cc89deb084004ddae4b","datavalue":{"value":{"entity-type":"item","numeric-id":1860,"id":"Q1860"},"type":"wikibase-entityid"}},"type":"statement","id":"Q105743918$A04688AE-2938-4646-A31E-198C6678038B","rank":"normal"}],"P1476":[{"mainsnak":{"snaktype":"value","property":"P1476","hash":"1163ea7e6cce74f0eefc7a29c8487d839abfc367","datavalue":{"value":{"text":"Allium lopadusanum (Liliaceae), a New Species from Lampedusa (Sicily)","language":"en"},"type":"monolingualtext"}},"type":"statement","id":"Q105743918$F718B3B0-3DCA-46CA-86CF-A63750767A10","rank":"normal","references":[{"hash":"8408ce78a981253dfb4653c56fef4ce7302d3150","snaks":{"P248":[{"snaktype":"value","property":"P248","hash":"71000ade3e2d3e332c52d5e596bcb34c3efeef6f","datavalue":{"value":{"entity-type":"item","numeric-id":1420342,"id":"Q1420342"},"type":"wikibase-entityid"}}],"P854":[{"snaktype":"value","property":"P854","hash":"94bdf5a2a925ff5aa8918ee4c2fda9dc8062c34e","datavalue":{"value":"https:\/\/www.jstor.org\/stable\/3996306","type":"string"}}]},"snaks-order":["P248","P854"]}]}],"P31":[{"mainsnak":{"snaktype":"value","property":"P31","hash":"29465f78f13add11b617f0de4ade56cd1122c19c","datavalue":{"value":{"entity-type":"item","numeric-id":13442814,"id":"Q13442814"},"type":"wikibase-entityid"}},"type":"statement","id":"Q105743918$97926E20-FAED-4CA4-8D9E-2E2843ACD21E","rank":"normal","references":[{"hash":"8408ce78a981253dfb4653c56fef4ce7302d3150","snaks":{"P248":[{"snaktype":"value","property":"P248","hash":"71000ade3e2d3e332c52d5e596bcb34c3efeef6f","datavalue":{"value":{"entity-type":"item","numeric-id":1420342,"id":"Q1420342"},"type":"wikibase-entityid"}}],"P854":[{"snaktype":"value","property":"P854","hash":"94bdf5a2a925ff5aa8918ee4c2fda9dc8062c34e","datavalue":{"value":"https:\/\/www.jstor.org\/stable\/3996306","type":"string"}}]},"snaks-order":["P248","P854"]}]}],"P577":[{"mainsnak":{"snaktype":"value","property":"P577","hash":"9a17e46d4a2f0a91dbc56bf472d514cba2368eaf","datavalue":{"value":{"time":"+1986-00-00T00:00:00Z","timezone":0,"before":0,"after":0,"precision":9,"calendarmodel":"http:\/\/www.wikidata.org\/entity\/Q1985727"},"type":"time"}},"type":"statement","id":"Q105743918$641C4895-A058-480A-A278-4E34A0D2479C","rank":"normal","references":[{"hash":"8408ce78a981253dfb4653c56fef4ce7302d3150","snaks":{"P248":[{"snaktype":"value","property":"P248","hash":"71000ade3e2d3e332c52d5e596bcb34c3efeef6f","datavalue":{"value":{"entity-type":"item","numeric-id":1420342,"id":"Q1420342"},"type":"wikibase-entityid"}}],"P854":[{"snaktype":"value","property":"P854","hash":"94bdf5a2a925ff5aa8918ee4c2fda9dc8062c34e","datavalue":{"value":"https:\/\/www.jstor.org\/stable\/3996306","type":"string"}}]},"snaks-order":["P248","P854"]}]}],"P2093":[{"mainsnak":{"snaktype":"value","property":"P2093","hash":"1fe694103159413d47d092e517346eb37b1058dd","datavalue":{"value":"Giuseppina Bartolo","type":"string"}},"type":"statement","qualifiers":{"P1545":[{"snaktype":"value","property":"P1545","hash":"2a1ced1dca90648ea7e306acbadd74fc81a10722","datavalue":{"value":"1","type":"string"}}]},"qualifiers-order":["P1545"],"id":"Q105743918$4B2B796C-5AF8-4933-B4D1-CCEEF7A132CA","rank":"normal","references":[{"hash":"8408ce78a981253dfb4653c56fef4ce7302d3150","snaks":{"P248":[{"snaktype":"value","property":"P248","hash":"71000ade3e2d3e332c52d5e596bcb34c3efeef6f","datavalue":{"value":{"entity-type":"item","numeric-id":1420342,"id":"Q1420342"},"type":"wikibase-entityid"}}],"P854":[{"snaktype":"value","property":"P854","hash":"94bdf5a2a925ff5aa8918ee4c2fda9dc8062c34e","datavalue":{"value":"https:\/\/www.jstor.org\/stable\/3996306","type":"string"}}]},"snaks-order":["P248","P854"]}]},{"mainsnak":{"snaktype":"value","property":"P2093","hash":"161499798147731ba31661e941d312bc53906041","datavalue":{"value":"Salvatore Brullo","type":"string"}},"type":"statement","qualifiers":{"P1545":[{"snaktype":"value","property":"P1545","hash":"7241753c62a310cf84895620ea82250dcea65835","datavalue":{"value":"2","type":"string"}}]},"qualifiers-order":["P1545"],"id":"Q105743918$5172C6C5-73A2-4AEB-9229-BB6DDAD1C6A0","rank":"normal","references":[{"hash":"8408ce78a981253dfb4653c56fef4ce7302d3150","snaks":{"P248":[{"snaktype":"value","property":"P248","hash":"71000ade3e2d3e332c52d5e596bcb34c3efeef6f","datavalue":{"value":{"entity-type":"item","numeric-id":1420342,"id":"Q1420342"},"type":"wikibase-entityid"}}],"P854":[{"snaktype":"value","property":"P854","hash":"94bdf5a2a925ff5aa8918ee4c2fda9dc8062c34e","datavalue":{"value":"https:\/\/www.jstor.org\/stable\/3996306","type":"string"}}]},"snaks-order":["P248","P854"]}]},{"mainsnak":{"snaktype":"value","property":"P2093","hash":"e149c359421c20951780e93765aa4f85af2ad52e","datavalue":{"value":"Pietro Pavone","type":"string"}},"type":"statement","qualifiers":{"P1545":[{"snaktype":"value","property":"P1545","hash":"0e979f28bf306fefdcd352b4eb8dee5da2153a6d","datavalue":{"value":"3","type":"string"}}]},"qualifiers-order":["P1545"],"id":"Q105743918$1B245665-65D9-48A5-8C59-A7FB35E37679","rank":"normal","references":[{"hash":"8408ce78a981253dfb4653c56fef4ce7302d3150","snaks":{"P248":[{"snaktype":"value","property":"P248","hash":"71000ade3e2d3e332c52d5e596bcb34c3efeef6f","datavalue":{"value":{"entity-type":"item","numeric-id":1420342,"id":"Q1420342"},"type":"wikibase-entityid"}}],"P854":[{"snaktype":"value","property":"P854","hash":"94bdf5a2a925ff5aa8918ee4c2fda9dc8062c34e","datavalue":{"value":"https:\/\/www.jstor.org\/stable\/3996306","type":"string"}}]},"snaks-order":["P248","P854"]}]}],"P1433":[{"mainsnak":{"snaktype":"value","property":"P1433","hash":"ad755d34ad4505b3a1dcd4a698a14bce870a0615","datavalue":{"value":{"entity-type":"item","numeric-id":2675951,"id":"Q2675951"},"type":"wikibase-entityid"}},"type":"statement","id":"Q105743918$030BDE6F-1629-47A7-9829-3DEE2182F150","rank":"normal","references":[{"hash":"8408ce78a981253dfb4653c56fef4ce7302d3150","snaks":{"P248":[{"snaktype":"value","property":"P248","hash":"71000ade3e2d3e332c52d5e596bcb34c3efeef6f","datavalue":{"value":{"entity-type":"item","numeric-id":1420342,"id":"Q1420342"},"type":"wikibase-entityid"}}],"P854":[{"snaktype":"value","property":"P854","hash":"94bdf5a2a925ff5aa8918ee4c2fda9dc8062c34e","datavalue":{"value":"https:\/\/www.jstor.org\/stable\/3996306","type":"string"}}]},"snaks-order":["P248","P854"]}]}],"P478":[{"mainsnak":{"snaktype":"value","property":"P478","hash":"c6d9ab79d7e0a7bda3a388ebe3dd94a2da80b455","datavalue":{"value":"16","type":"string"}},"type":"statement","id":"Q105743918$9F027078-3362-431A-BAE9-104DBAEAE511","rank":"normal","references":[{"hash":"8408ce78a981253dfb4653c56fef4ce7302d3150","snaks":{"P248":[{"snaktype":"value","property":"P248","hash":"71000ade3e2d3e332c52d5e596bcb34c3efeef6f","datavalue":{"value":{"entity-type":"item","numeric-id":1420342,"id":"Q1420342"},"type":"wikibase-entityid"}}],"P854":[{"snaktype":"value","property":"P854","hash":"94bdf5a2a925ff5aa8918ee4c2fda9dc8062c34e","datavalue":{"value":"https:\/\/www.jstor.org\/stable\/3996306","type":"string"}}]},"snaks-order":["P248","P854"]}]}],"P433":[{"mainsnak":{"snaktype":"value","property":"P433","hash":"962ed10012ef254020e2a8c8a6c8ba7647d35a12","datavalue":{"value":"1","type":"string"}},"type":"statement","id":"Q105743918$D4BA6074-FD53-4675-8D7C-8C214975BFC6","rank":"normal","references":[{"hash":"8408ce78a981253dfb4653c56fef4ce7302d3150","snaks":{"P248":[{"snaktype":"value","property":"P248","hash":"71000ade3e2d3e332c52d5e596bcb34c3efeef6f","datavalue":{"value":{"entity-type":"item","numeric-id":1420342,"id":"Q1420342"},"type":"wikibase-entityid"}}],"P854":[{"snaktype":"value","property":"P854","hash":"94bdf5a2a925ff5aa8918ee4c2fda9dc8062c34e","datavalue":{"value":"https:\/\/www.jstor.org\/stable\/3996306","type":"string"}}]},"snaks-order":["P248","P854"]}]}],"P304":[{"mainsnak":{"snaktype":"value","property":"P304","hash":"3b88738ced1cf84f9d4e94adc914d41034492775","datavalue":{"value":"89-93","type":"string"}},"type":"statement","id":"Q105743918$F199F168-C27A-4083-A523-A84748C0320E","rank":"normal","references":[{"hash":"8408ce78a981253dfb4653c56fef4ce7302d3150","snaks":{"P248":[{"snaktype":"value","property":"P248","hash":"71000ade3e2d3e332c52d5e596bcb34c3efeef6f","datavalue":{"value":{"entity-type":"item","numeric-id":1420342,"id":"Q1420342"},"type":"wikibase-entityid"}}],"P854":[{"snaktype":"value","property":"P854","hash":"94bdf5a2a925ff5aa8918ee4c2fda9dc8062c34e","datavalue":{"value":"https:\/\/www.jstor.org\/stable\/3996306","type":"string"}}]},"snaks-order":["P248","P854"]}]}],"P888":[{"mainsnak":{"snaktype":"value","property":"P888","hash":"c4a8b3b709e456cebfdfa9ee47fd860368de65f9","datavalue":{"value":"3996306","type":"string"}},"type":"statement","id":"Q105743918$0CBEED53-21A6-4537-B3CE-923D2DAF190C","rank":"normal","references":[{"hash":"8408ce78a981253dfb4653c56fef4ce7302d3150","snaks":{"P248":[{"snaktype":"value","property":"P248","hash":"71000ade3e2d3e332c52d5e596bcb34c3efeef6f","datavalue":{"value":{"entity-type":"item","numeric-id":1420342,"id":"Q1420342"},"type":"wikibase-entityid"}}],"P854":[{"snaktype":"value","property":"P854","hash":"94bdf5a2a925ff5aa8918ee4c2fda9dc8062c34e","datavalue":{"value":"https:\/\/www.jstor.org\/stable\/3996306","type":"string"}}]},"snaks-order":["P248","P854"]}]}]},"sitelinks":[]}</text>
      <sha1>dsrn36ys6k798omui95bousung8h224</sha1>
    </revision>
  </page>
</mediawiki>
