{
  "head" : {
    "vars" : [ "o", "p" ]
  },
  "results" : {
    "bindings" : [ {
      "o" : {
        "type" : "uri",
        "value" : "http://www.wikidata.org/entity/Q28822163"
      },
      "p" : {
        "type" : "uri",
        "value" : "http://www.wikidata.org/prop/direct/P2860"
      }
    }, {
      "o" : {
        "type" : "uri",
        "value" : "http://www.wikidata.org/entity/Q30317049"
      },
      "p" : {
        "type" : "uri",
        "value" : "http://www.wikidata.org/prop/direct/P2860"
      }
    }, {
      "o" : {
        "type" : "uri",
        "value" : "http://www.wikidata.org/entity/Q31041030"
      },
      "p" : {
        "type" : "uri",
        "value" : "http://www.wikidata.org/prop/direct/P2860"
      }
    }, {
      "o" : {
        "type" : "uri",
        "value" : "http://www.wikidata.org/entity/Q55540310"
      },
      "p" : {
        "type" : "uri",
        "value" : "http://www.wikidata.org/prop/direct/P2860"
      }
    }, {
      "o" : {
        "type" : "uri",
        "value" : "http://www.wikidata.org/entity/Q55886027"
      },
      "p" : {
        "type" : "uri",
        "value" : "http://www.wikidata.org/prop/direct/P2860"
      }
    }, {
      "p" : {
        "type" : "uri",
        "value" : "http://www.wikidata.org/prop/direct/P50"
      },
      "o" : {
        "type" : "uri",
        "value" : "http://www.wikidata.org/entity/Q2741049"
      }
    }, {
      "p" : {
        "type" : "uri",
        "value" : "http://www.wikidata.org/prop/direct/P1433"
      },
      "o" : {
        "type" : "uri",
        "value" : "http://www.wikidata.org/entity/Q22965468"
      }
    }, {
      "p" : {
        "type" : "uri",
        "value" : "http://www.wikidata.org/prop/direct/P1433"
      },
      "o" : {
        "type" : "uri",
        "value" : "http://www.wikidata.org/entity/Q22965468"
      }
    }, {
      "p" : {
        "type" : "uri",
        "value" : "http://www.wikidata.org/prop/direct/P1433"
      },
      "o" : {
        "type" : "uri",
        "value" : "http://www.wikidata.org/entity/Q22965468"
      }
    }, {
      "p" : {
        "type" : "uri",
        "value" : "http://www.wikidata.org/prop/direct/P2860"
      },
      "o" : {
        "type" : "uri",
        "value" : "http://www.wikidata.org/entity/Q24683485"
      }
    }, {
      "p" : {
        "type" : "uri",
        "value" : "http://www.wikidata.org/prop/direct/P2860"
      },
      "o" : {
        "type" : "uri",
        "value" : "http://www.wikidata.org/entity/Q29577919"
      }
    }, {
      "p" : {
        "type" : "uri",
        "value" : "http://www.wikidata.org/prop/direct/P2860"
      },
      "o" : {
        "type" : "uri",
        "value" : "http://www.wikidata.org/entity/Q29615354"
      }
    }, {
      "p" : {
        "type" : "uri",
        "value" : "http://www.wikidata.org/prop/direct/P2860"
      },
      "o" : {
        "type" : "uri",
        "value" : "http://www.wikidata.org/entity/Q30574998"
      }
    }, {
      "p" : {
        "type" : "uri",
        "value" : "http://www.wikidata.org/prop/direct/P2860"
      },
      "o" : {
        "type" : "uri",
        "value" : "http://www.wikidata.org/entity/Q30665615"
      }
    }, {
      "p" : {
        "type" : "uri",
        "value" : "http://www.wikidata.org/prop/direct/P2860"
      },
      "o" : {
        "type" : "uri",
        "value" : "http://www.wikidata.org/entity/Q30881758"
      }
    }, {
      "p" : {
        "type" : "uri",
        "value" : "http://www.wikidata.org/prop/direct/P2860"
      },
      "o" : {
        "type" : "uri",
        "value" : "http://www.wikidata.org/entity/Q33536456"
      }
    }, {
      "p" : {
        "type" : "uri",
        "value" : "http://www.wikidata.org/prop/direct/P50"
      },
      "o" : {
        "type" : "uri",
        "value" : "http://www.wikidata.org/entity/Q36590979"
      }
    }, {
      "p" : {
        "type" : "uri",
        "value" : "http://www.wikidata.org/prop/direct/P2860"
      },
      "o" : {
        "type" : "uri",
        "value" : "http://www.wikidata.org/entity/Q48062382"
      }
    }, {
      "p" : {
        "type" : "uri",
        "value" : "http://www.wikidata.org/prop/direct/P2860"
      },
      "o" : {
        "type" : "uri",
        "value" : "http://www.wikidata.org/entity/Q77140964"
      }
    } ]
  }
}