{
  "head" : {
    "vars" : [ "o", "p" ]
  },
  "results" : {
    "bindings" : [ {
      "o" : {
        "type" : "uri",
        "value" : "http://www.wikidata.org/entity/Q42371808"
      },
      "p" : {
        "type" : "uri",
        "value" : "http://www.wikidata.org/prop/direct/P2860"
      }
    }, {
      "o" : {
        "type" : "uri",
        "value" : "http://www.wikidata.org/entity/Q91237148"
      },
      "p" : {
        "type" : "uri",
        "value" : "http://www.wikidata.org/prop/direct/P2860"
      }
    }, {
      "o" : {
        "type" : "uri",
        "value" : "http://www.wikidata.org/entity/Q107670319"
      },
      "p" : {
        "type" : "uri",
        "value" : "http://www.wikidata.org/prop/direct/P2860"
      }
    }, {
      "o" : {
        "type" : "uri",
        "value" : "http://www.wikidata.org/entity/Q110694225"
      },
      "p" : {
        "type" : "uri",
        "value" : "http://www.wikidata.org/prop/direct/P2860"
      }
    }, {
      "p" : {
        "type" : "uri",
        "value" : "http://www.wikidata.org/prop/direct/P921"
      },
      "o" : {
        "type" : "uri",
        "value" : "http://www.wikidata.org/entity/Q171184"
      }
    }, {
      "p" : {
        "type" : "uri",
        "value" : "http://www.wikidata.org/prop/direct/P1433"
      },
      "o" : {
        "type" : "uri",
        "value" : "http://www.wikidata.org/entity/Q4248868"
      }
    }, {
      "p" : {
        "type" : "uri",
        "value" : "http://www.wikidata.org/prop/direct/P50"
      },
      "o" : {
        "type" : "uri",
        "value" : "http://www.wikidata.org/entity/Q26713561"
      }
    }, {
      "p" : {
        "type" : "uri",
        "value" : "http://www.wikidata.org/prop/direct/P2860"
      },
      "o" : {
        "type" : "uri",
        "value" : "http://www.wikidata.org/entity/Q26778438"
      }
    }, {
      "p" : {
        "type" : "uri",
        "value" : "http://www.wikidata.org/prop/direct/P2860"
      },
      "o" : {
        "type" : "uri",
        "value" : "http://www.wikidata.org/entity/Q27860864"
      }
    }, {
      "p" : {
        "type" : "uri",
        "value" : "http://www.wikidata.org/prop/direct/P2860"
      },
      "o" : {
        "type" : "uri",
        "value" : "http://www.wikidata.org/entity/Q28948183"
      }
    }, {
      "p" : {
        "type" : "uri",
        "value" : "http://www.wikidata.org/prop/direct/P2860"
      },
      "o" : {
        "type" : "uri",
        "value" : "http://www.wikidata.org/entity/Q28953144"
      }
    }, {
      "p" : {
        "type" : "uri",
        "value" : "http://www.wikidata.org/prop/direct/P2860"
      },
      "o" : {
        "type" : "uri",
        "value" : "http://www.wikidata.org/entity/Q28960428"
      }
    }, {
      "p" : {
        "type" : "uri",
        "value" : "http://www.wikidata.org/prop/direct/P2860"
      },
      "o" : {
        "type" : "uri",
        "value" : "http://www.wikidata.org/entity/Q29037014"
      }
    }, {
      "p" : {
        "type" : "uri",
        "value" : "http://www.wikidata.org/prop/direct/P2860"
      },
      "o" : {
        "type" : "uri",
        "value" : "http://www.wikidata.org/entity/Q29547617"
      }
    }, {
      "p" : {
        "type" : "uri",
        "value" : "http://www.wikidata.org/prop/direct/P921"
      },
      "o" : {
        "type" : "uri",
        "value" : "http://www.wikidata.org/entity/Q52800401"
      }
    }, {
      "o" : {
        "type" : "uri",
        "value" : "http://www.wikidata.org/entity/Q43372111"
      },
      "p" : {
        "type" : "uri",
        "value" : "http://www.wikidata.org/prop/direct/P248"
      }
    }, {
      "o" : {
        "type" : "uri",
        "value" : "http://www.wikidata.org/entity/Q43372113"
      },
      "p" : {
        "type" : "uri",
        "value" : "http://www.wikidata.org/prop/direct/P248"
      }
    }, {
      "o" : {
        "type" : "uri",
        "value" : "http://www.wikidata.org/entity/Q43372117"
      },
      "p" : {
        "type" : "uri",
        "value" : "http://www.wikidata.org/prop/direct/P248"
      }
    }, {
      "p" : {
        "type" : "uri",
        "value" : "http://www.wikidata.org/prop/direct/P2860"
      },
      "o" : {
        "type" : "uri",
        "value" : "http://www.wikidata.org/entity/Q33105812"
      }
    }, {
      "p" : {
        "type" : "uri",
        "value" : "http://www.wikidata.org/prop/direct/P2860"
      },
      "o" : {
        "type" : "uri",
        "value" : "http://www.wikidata.org/entity/Q33775607"
      }
    }, {
      "p" : {
        "type" : "uri",
        "value" : "http://www.wikidata.org/prop/direct/P2860"
      },
      "o" : {
        "type" : "uri",
        "value" : "http://www.wikidata.org/entity/Q34190219"
      }
    }, {
      "p" : {
        "type" : "uri",
        "value" : "http://www.wikidata.org/prop/direct/P2860"
      },
      "o" : {
        "type" : "uri",
        "value" : "http://www.wikidata.org/entity/Q35940348"
      }
    }, {
      "p" : {
        "type" : "uri",
        "value" : "http://www.wikidata.org/prop/direct/P2860"
      },
      "o" : {
        "type" : "uri",
        "value" : "http://www.wikidata.org/entity/Q38388309"
      }
    }, {
      "p" : {
        "type" : "uri",
        "value" : "http://www.wikidata.org/prop/direct/P2860"
      },
      "o" : {
        "type" : "uri",
        "value" : "http://www.wikidata.org/entity/Q39398345"
      }
    }, {
      "p" : {
        "type" : "uri",
        "value" : "http://www.wikidata.org/prop/direct/P2860"
      },
      "o" : {
        "type" : "uri",
        "value" : "http://www.wikidata.org/entity/Q39437919"
      }
    }, {
      "p" : {
        "type" : "uri",
        "value" : "http://www.wikidata.org/prop/direct/P2860"
      },
      "o" : {
        "type" : "uri",
        "value" : "http://www.wikidata.org/entity/Q39947540"
      }
    }, {
      "p" : {
        "type" : "uri",
        "value" : "http://www.wikidata.org/prop/direct/P2860"
      },
      "o" : {
        "type" : "uri",
        "value" : "http://www.wikidata.org/entity/Q44810859"
      }
    }, {
      "p" : {
        "type" : "uri",
        "value" : "http://www.wikidata.org/prop/direct/P2860"
      },
      "o" : {
        "type" : "uri",
        "value" : "http://www.wikidata.org/entity/Q55757985"
      }
    }, {
      "p" : {
        "type" : "uri",
        "value" : "http://www.wikidata.org/prop/direct/P2860"
      },
      "o" : {
        "type" : "uri",
        "value" : "http://www.wikidata.org/entity/Q55764524"
      }
    }, {
      "p" : {
        "type" : "uri",
        "value" : "http://www.wikidata.org/prop/direct/P2860"
      },
      "o" : {
        "type" : "uri",
        "value" : "http://www.wikidata.org/entity/Q55878692"
      }
    }, {
      "p" : {
        "type" : "uri",
        "value" : "http://www.wikidata.org/prop/direct/P2860"
      },
      "o" : {
        "type" : "uri",
        "value" : "http://www.wikidata.org/entity/Q57111185"
      }
    }, {
      "p" : {
        "type" : "uri",
        "value" : "http://www.wikidata.org/prop/direct/P2860"
      },
      "o" : {
        "type" : "uri",
        "value" : "http://www.wikidata.org/entity/Q61444705"
      }
    }, {
      "p" : {
        "type" : "uri",
        "value" : "http://www.wikidata.org/prop/direct/P2860"
      },
      "o" : {
        "type" : "uri",
        "value" : "http://www.wikidata.org/entity/Q64081999"
      }
    }, {
      "p" : {
        "type" : "uri",
        "value" : "http://www.wikidata.org/prop/direct/P2860"
      },
      "o" : {
        "type" : "uri",
        "value" : "http://www.wikidata.org/entity/Q64082011"
      }
    }, {
      "p" : {
        "type" : "uri",
        "value" : "http://www.wikidata.org/prop/direct/P2860"
      },
      "o" : {
        "type" : "uri",
        "value" : "http://www.wikidata.org/entity/Q64082038"
      }
    }, {
      "p" : {
        "type" : "uri",
        "value" : "http://www.wikidata.org/prop/direct/P2860"
      },
      "o" : {
        "type" : "uri",
        "value" : "http://www.wikidata.org/entity/Q93625792"
      }
    }, {
      "p" : {
        "type" : "uri",
        "value" : "http://www.wikidata.org/prop/direct/P2860"
      },
      "o" : {
        "type" : "uri",
        "value" : "http://www.wikidata.org/entity/Q101634849"
      }
    } ]
  }
}