{
  "head" : {
    "vars" : [ "o", "p" ]
  },
  "results" : {
    "bindings" : [ {
      "o" : {
        "type" : "uri",
        "value" : "http://www.wikidata.org/entity/Q57335044"
      },
      "p" : {
        "type" : "uri",
        "value" : "http://www.wikidata.org/prop/direct/P2860"
      }
    }, {
      "p" : {
        "type" : "uri",
        "value" : "http://www.wikidata.org/prop/direct/P1433"
      },
      "o" : {
        "type" : "uri",
        "value" : "http://www.wikidata.org/entity/Q21386054"
      }
    }, {
      "p" : {
        "type" : "uri",
        "value" : "http://www.wikidata.org/prop/direct/P1433"
      },
      "o" : {
        "type" : "uri",
        "value" : "http://www.wikidata.org/entity/Q21386054"
      }
    }, {
      "p" : {
        "type" : "uri",
        "value" : "http://www.wikidata.org/prop/direct/P2860"
      },
      "o" : {
        "type" : "uri",
        "value" : "http://www.wikidata.org/entity/Q33811465"
      }
    }, {
      "p" : {
        "type" : "uri",
        "value" : "http://www.wikidata.org/prop/direct/P2860"
      },
      "o" : {
        "type" : "uri",
        "value" : "http://www.wikidata.org/entity/Q34677528"
      }
    }, {
      "p" : {
        "type" : "uri",
        "value" : "http://www.wikidata.org/prop/direct/P2860"
      },
      "o" : {
        "type" : "uri",
        "value" : "http://www.wikidata.org/entity/Q51444877"
      }
    }, {
      "p" : {
        "type" : "uri",
        "value" : "http://www.wikidata.org/prop/direct/P2860"
      },
      "o" : {
        "type" : "uri",
        "value" : "http://www.wikidata.org/entity/Q51506334"
      }
    }, {
      "p" : {
        "type" : "uri",
        "value" : "http://www.wikidata.org/prop/direct/P2860"
      },
      "o" : {
        "type" : "uri",
        "value" : "http://www.wikidata.org/entity/Q51506513"
      }
    }, {
      "p" : {
        "type" : "uri",
        "value" : "http://www.wikidata.org/prop/direct/P2860"
      },
      "o" : {
        "type" : "uri",
        "value" : "http://www.wikidata.org/entity/Q51506513"
      }
    }, {
      "p" : {
        "type" : "uri",
        "value" : "http://www.wikidata.org/prop/direct/P2860"
      },
      "o" : {
        "type" : "uri",
        "value" : "http://www.wikidata.org/entity/Q54701177"
      }
    }, {
      "p" : {
        "type" : "uri",
        "value" : "http://www.wikidata.org/prop/direct/P2860"
      },
      "o" : {
        "type" : "uri",
        "value" : "http://www.wikidata.org/entity/Q55918567"
      }
    }, {
      "p" : {
        "type" : "uri",
        "value" : "http://www.wikidata.org/prop/direct/P2860"
      },
      "o" : {
        "type" : "uri",
        "value" : "http://www.wikidata.org/entity/Q56009234"
      }
    }, {
      "p" : {
        "type" : "uri",
        "value" : "http://www.wikidata.org/prop/direct/P2860"
      },
      "o" : {
        "type" : "uri",
        "value" : "http://www.wikidata.org/entity/Q56098650"
      }
    }, {
      "p" : {
        "type" : "uri",
        "value" : "http://www.wikidata.org/prop/direct/P2860"
      },
      "o" : {
        "type" : "uri",
        "value" : "http://www.wikidata.org/entity/Q56099203"
      }
    }, {
      "p" : {
        "type" : "uri",
        "value" : "http://www.wikidata.org/prop/direct/P2860"
      },
      "o" : {
        "type" : "uri",
        "value" : "http://www.wikidata.org/entity/Q56099508"
      }
    }, {
      "p" : {
        "type" : "uri",
        "value" : "http://www.wikidata.org/prop/direct/P2860"
      },
      "o" : {
        "type" : "uri",
        "value" : "http://www.wikidata.org/entity/Q56210457"
      }
    }, {
      "p" : {
        "type" : "uri",
        "value" : "http://www.wikidata.org/prop/direct/P2860"
      },
      "o" : {
        "type" : "uri",
        "value" : "http://www.wikidata.org/entity/Q59485999"
      }
    }, {
      "p" : {
        "type" : "uri",
        "value" : "http://www.wikidata.org/prop/direct/P2860"
      },
      "o" : {
        "type" : "uri",
        "value" : "http://www.wikidata.org/entity/Q97059700"
      }
    }, {
      "p" : {
        "type" : "uri",
        "value" : "http://www.wikidata.org/prop/direct/P2860"
      },
      "o" : {
        "type" : "uri",
        "value" : "http://www.wikidata.org/entity/Q97059793"
      }
    }, {
      "p" : {
        "type" : "uri",
        "value" : "http://www.wikidata.org/prop/direct/P2860"
      },
      "o" : {
        "type" : "uri",
        "value" : "http://www.wikidata.org/entity/Q99656226"
      }
    }, {
      "p" : {
        "type" : "uri",
        "value" : "http://www.wikidata.org/prop/direct/P2860"
      },
      "o" : {
        "type" : "uri",
        "value" : "http://www.wikidata.org/entity/Q99840820"
      }
    }, {
      "p" : {
        "type" : "uri",
        "value" : "http://www.wikidata.org/prop/direct/P2860"
      },
      "o" : {
        "type" : "uri",
        "value" : "http://www.wikidata.org/entity/Q99845944"
      }
    } ]
  }
}