{
  "head" : {
    "vars" : [ "o", "p" ]
  },
  "results" : {
    "bindings" : [ {
      "o" : {
        "type" : "uri",
        "value" : "http://www.wikidata.org/entity/Q21192536"
      },
      "p" : {
        "type" : "uri",
        "value" : "http://www.wikidata.org/prop/direct/P2860"
      }
    }, {
      "o" : {
        "type" : "uri",
        "value" : "http://www.wikidata.org/entity/Q42260451"
      },
      "p" : {
        "type" : "uri",
        "value" : "http://www.wikidata.org/prop/direct/P2860"
      }
    }, {
      "o" : {
        "type" : "uri",
        "value" : "http://www.wikidata.org/entity/Q56269743"
      },
      "p" : {
        "type" : "uri",
        "value" : "http://www.wikidata.org/prop/direct/P2860"
      }
    }, {
      "o" : {
        "type" : "uri",
        "value" : "http://www.wikidata.org/entity/Q59876540"
      },
      "p" : {
        "type" : "uri",
        "value" : "http://www.wikidata.org/prop/direct/P2860"
      }
    }, {
      "o" : {
        "type" : "uri",
        "value" : "http://www.wikidata.org/entity/Q59876574"
      },
      "p" : {
        "type" : "uri",
        "value" : "http://www.wikidata.org/prop/direct/P2860"
      }
    }, {
      "o" : {
        "type" : "uri",
        "value" : "http://www.wikidata.org/entity/Q98394972"
      },
      "p" : {
        "type" : "uri",
        "value" : "http://www.wikidata.org/prop/direct/P2860"
      }
    }, {
      "o" : {
        "type" : "uri",
        "value" : "http://www.wikidata.org/entity/Q104670429"
      },
      "p" : {
        "type" : "uri",
        "value" : "http://www.wikidata.org/prop/direct/P2860"
      }
    }, {
      "p" : {
        "type" : "uri",
        "value" : "http://www.wikidata.org/prop/direct/P921"
      },
      "o" : {
        "type" : "uri",
        "value" : "http://www.wikidata.org/entity/Q34"
      }
    }, {
      "p" : {
        "type" : "uri",
        "value" : "http://www.wikidata.org/prop/direct/P921"
      },
      "o" : {
        "type" : "uri",
        "value" : "http://www.wikidata.org/entity/Q34"
      }
    }, {
      "p" : {
        "type" : "uri",
        "value" : "http://www.wikidata.org/prop/direct/P921"
      },
      "o" : {
        "type" : "uri",
        "value" : "http://www.wikidata.org/entity/Q34"
      }
    }, {
      "p" : {
        "type" : "uri",
        "value" : "http://www.wikidata.org/prop/direct/P921"
      },
      "o" : {
        "type" : "uri",
        "value" : "http://www.wikidata.org/entity/Q174726"
      }
    }, {
      "p" : {
        "type" : "uri",
        "value" : "http://www.wikidata.org/prop/direct/P1433"
      },
      "o" : {
        "type" : "uri",
        "value" : "http://www.wikidata.org/entity/Q15755501"
      }
    }, {
      "p" : {
        "type" : "uri",
        "value" : "http://www.wikidata.org/prop/direct/P50"
      },
      "o" : {
        "type" : "uri",
        "value" : "http://www.wikidata.org/entity/Q21510517"
      }
    }, {
      "p" : {
        "type" : "uri",
        "value" : "http://www.wikidata.org/prop/direct/P2860"
      },
      "o" : {
        "type" : "uri",
        "value" : "http://www.wikidata.org/entity/Q28306496"
      }
    }, {
      "p" : {
        "type" : "uri",
        "value" : "http://www.wikidata.org/prop/direct/P2860"
      },
      "o" : {
        "type" : "uri",
        "value" : "http://www.wikidata.org/entity/Q28306496"
      }
    }, {
      "p" : {
        "type" : "uri",
        "value" : "http://www.wikidata.org/prop/direct/P2860"
      },
      "o" : {
        "type" : "uri",
        "value" : "http://www.wikidata.org/entity/Q28959431"
      }
    }, {
      "p" : {
        "type" : "uri",
        "value" : "http://www.wikidata.org/prop/direct/P2860"
      },
      "o" : {
        "type" : "uri",
        "value" : "http://www.wikidata.org/entity/Q30987555"
      }
    }, {
      "p" : {
        "type" : "uri",
        "value" : "http://www.wikidata.org/prop/direct/P2860"
      },
      "o" : {
        "type" : "uri",
        "value" : "http://www.wikidata.org/entity/Q34337848"
      }
    }, {
      "p" : {
        "type" : "uri",
        "value" : "http://www.wikidata.org/prop/direct/P2860"
      },
      "o" : {
        "type" : "uri",
        "value" : "http://www.wikidata.org/entity/Q50772865"
      }
    }, {
      "p" : {
        "type" : "uri",
        "value" : "http://www.wikidata.org/prop/direct/P921"
      },
      "o" : {
        "type" : "uri",
        "value" : "http://www.wikidata.org/entity/Q52800401"
      }
    }, {
      "p" : {
        "type" : "uri",
        "value" : "http://www.wikidata.org/prop/direct/P2860"
      },
      "o" : {
        "type" : "uri",
        "value" : "http://www.wikidata.org/entity/Q56269900"
      }
    }, {
      "p" : {
        "type" : "uri",
        "value" : "http://www.wikidata.org/prop/direct/P2860"
      },
      "o" : {
        "type" : "uri",
        "value" : "http://www.wikidata.org/entity/Q59876591"
      }
    }, {
      "p" : {
        "type" : "uri",
        "value" : "http://www.wikidata.org/prop/direct/P2860"
      },
      "o" : {
        "type" : "uri",
        "value" : "http://www.wikidata.org/entity/Q59876595"
      }
    }, {
      "p" : {
        "type" : "uri",
        "value" : "http://www.wikidata.org/prop/direct/P2860"
      },
      "o" : {
        "type" : "uri",
        "value" : "http://www.wikidata.org/entity/Q59876600"
      }
    }, {
      "p" : {
        "type" : "uri",
        "value" : "http://www.wikidata.org/prop/direct/P2860"
      },
      "o" : {
        "type" : "uri",
        "value" : "http://www.wikidata.org/entity/Q105111994"
      }
    } ]
  }
}