{
  "head" : {
    "vars" : [ "o", "p" ]
  },
  "results" : {
    "bindings" : [ {
      "p" : {
        "type" : "uri",
        "value" : "http://www.wikidata.org/prop/direct/P921"
      },
      "o" : {
        "type" : "uri",
        "value" : "http://www.wikidata.org/entity/Q44626"
      }
    }, {
      "p" : {
        "type" : "uri",
        "value" : "http://www.wikidata.org/prop/direct/P921"
      },
      "o" : {
        "type" : "uri",
        "value" : "http://www.wikidata.org/entity/Q44626"
      }
    }, {
      "p" : {
        "type" : "uri",
        "value" : "http://www.wikidata.org/prop/direct/P1433"
      },
      "o" : {
        "type" : "uri",
        "value" : "http://www.wikidata.org/entity/Q5184698"
      }
    }, {
      "p" : {
        "type" : "uri",
        "value" : "http://www.wikidata.org/prop/direct/P50"
      },
      "o" : {
        "type" : "uri",
        "value" : "http://www.wikidata.org/entity/Q21177751"
      }
    }, {
      "p" : {
        "type" : "uri",
        "value" : "http://www.wikidata.org/prop/direct/P921"
      },
      "o" : {
        "type" : "uri",
        "value" : "http://www.wikidata.org/entity/Q21351285"
      }
    }, {
      "p" : {
        "type" : "uri",
        "value" : "http://www.wikidata.org/prop/direct/P50"
      },
      "o" : {
        "type" : "uri",
        "value" : "http://www.wikidata.org/entity/Q57593069"
      }
    }, {
      "o" : {
        "type" : "uri",
        "value" : "http://www.wikidata.org/entity/Q90069393"
      },
      "p" : {
        "type" : "uri",
        "value" : "http://www.wikidata.org/prop/direct/P2860"
      }
    }, {
      "o" : {
        "type" : "uri",
        "value" : "http://www.wikidata.org/entity/Q106698578"
      },
      "p" : {
        "type" : "uri",
        "value" : "http://www.wikidata.org/prop/direct/P2860"
      }
    }, {
      "o" : {
        "type" : "uri",
        "value" : "http://www.wikidata.org/entity/Q110666496"
      },
      "p" : {
        "type" : "uri",
        "value" : "http://www.wikidata.org/prop/direct/P2860"
      }
    }, {
      "o" : {
        "type" : "uri",
        "value" : "http://www.wikidata.org/entity/Q110667990"
      },
      "p" : {
        "type" : "uri",
        "value" : "http://www.wikidata.org/prop/direct/P2860"
      }
    }, {
      "o" : {
        "type" : "uri",
        "value" : "http://www.wikidata.org/entity/Q110668709"
      },
      "p" : {
        "type" : "uri",
        "value" : "http://www.wikidata.org/prop/direct/P2860"
      }
    }, {
      "o" : {
        "type" : "uri",
        "value" : "http://www.wikidata.org/entity/Q110669694"
      },
      "p" : {
        "type" : "uri",
        "value" : "http://www.wikidata.org/prop/direct/P2860"
      }
    } ]
  }
}