{
  "head" : {
    "vars" : [ "o", "p" ]
  },
  "results" : {
    "bindings" : [ {
      "p" : {
        "type" : "uri",
        "value" : "http://www.wikidata.org/prop/direct/P921"
      },
      "o" : {
        "type" : "uri",
        "value" : "http://www.wikidata.org/entity/Q864826"
      }
    }, {
      "p" : {
        "type" : "uri",
        "value" : "http://www.wikidata.org/prop/direct/P1433"
      },
      "o" : {
        "type" : "uri",
        "value" : "http://www.wikidata.org/entity/Q7126415"
      }
    }, {
      "p" : {
        "type" : "uri",
        "value" : "http://www.wikidata.org/prop/direct/P50"
      },
      "o" : {
        "type" : "uri",
        "value" : "http://www.wikidata.org/entity/Q104787929"
      }
    }, {
      "o" : {
        "type" : "uri",
        "value" : "http://www.wikidata.org/entity/Q46267404"
      },
      "p" : {
        "type" : "uri",
        "value" : "http://www.wikidata.org/prop/direct/P2860"
      }
    }, {
      "o" : {
        "type" : "uri",
        "value" : "http://www.wikidata.org/entity/Q57255133"
      },
      "p" : {
        "type" : "uri",
        "value" : "http://www.wikidata.org/prop/direct/P2860"
      }
    }, {
      "o" : {
        "type" : "uri",
        "value" : "http://www.wikidata.org/entity/Q92740437"
      },
      "p" : {
        "type" : "uri",
        "value" : "http://www.wikidata.org/prop/direct/P2860"
      }
    }, {
      "o" : {
        "type" : "uri",
        "value" : "http://www.wikidata.org/entity/Q110667228"
      },
      "p" : {
        "type" : "uri",
        "value" : "http://www.wikidata.org/prop/direct/P2860"
      }
    }, {
      "o" : {
        "type" : "uri",
        "value" : "http://www.wikidata.org/entity/Q110668066"
      },
      "p" : {
        "type" : "uri",
        "value" : "http://www.wikidata.org/prop/direct/P2860"
      }
    } ]
  }
}